viscid/__init__.py
viscid/__main__.py
viscid/_rc.py
viscid/amr_field.py
viscid/amr_grid.py
viscid/bucket.py
viscid/coordinate.py
viscid/cotr.py
viscid/dataset.py
viscid/dipole.py
viscid/extools.py
viscid/field.py
viscid/fluidtrace.py
viscid/grid.py
viscid/mapfield.py
viscid/multiplot.py
viscid/npdatetime.py
viscid/parallel.py
viscid/pyeval.py
viscid/rotation.py
viscid/seed.py
viscid/sliceutil.py
viscid/tree.py
viscid/verror.py
viscid/vjson.py
viscid/vutil.py
viscid/.libs/lib_fortfil.AAUNVOXULVNRBXEOBY7HZATSR66MWR3J.gfortran-win_amd64.dll
viscid/calculator/__init__.py
viscid/calculator/calc.py
viscid/calculator/cluster.py
viscid/calculator/ecfc.py
viscid/calculator/evaluator.py
viscid/calculator/minvar_tools.py
viscid/calculator/mpause.py
viscid/calculator/necalc.py
viscid/calculator/plasma.py
viscid/calculator/separator.py
viscid/calculator/topology.py
viscid/compat/__init__.py
viscid/compat/_xdmf_include.py
viscid/compat/element_tree.py
viscid/compat/ordered_dict_backport.py
viscid/compat/vimportlib.py
viscid/compat/futures/__init__.py
viscid/compat/futures/_base.py
viscid/compat/futures/process.py
viscid/compat/futures/thread.py
viscid/cython/__init__.py
viscid/cython/cyamr.cp37-win_amd64.pyd
viscid/cython/cycalc.cp37-win_amd64.pyd
viscid/cython/cyfield.cp37-win_amd64.pyd
viscid/cython/integrate.cp37-win_amd64.pyd
viscid/cython/null_tools.cp37-win_amd64.pyd
viscid/cython/streamline.cp37-win_amd64.pyd
viscid/plot/__init__.py
viscid/plot/_cm_cubehelix.py
viscid/plot/_cm_listed.py
viscid/plot/_cm_tools.py
viscid/plot/_mpl_grid1.py
viscid/plot/from_seaborn.py
viscid/plot/mpl.py
viscid/plot/mpl_direct_label.py
viscid/plot/mpl_extra.py
viscid/plot/mpl_style.py
viscid/plot/mvi.py
viscid/plot/vlab.py
viscid/plot/vpyplot.py
viscid/plot/vseaborn.py
viscid/plot/images/earth_1k.jpg
viscid/plot/images/earth_2k.jpg
viscid/plot/images/earth_4k.jpg
viscid/plot/images/earth_8k.jpg
viscid/plot/images/earth_faded_1k.jpg
viscid/plot/images/earth_faded_2k.jpg
viscid-1.0.0.dist-info/LICENSE
viscid-1.0.0.dist-info/METADATA
viscid-1.0.0.dist-info/WHEEL
viscid-1.0.0.dist-info/top_level.txt
viscid-1.0.0.dist-info/RECORD
