Metadata-Version: 2.1
Name: viscid
Version: 1.0.0
Summary: Visualize data on structured meshes in python
Home-page: https://github.com/viscid-hub/Viscid
Author: Kristofor Maynard
Author-email: k.maynard@unh.edu
License: MIT
Download-URL: https://github.com/viscid-hub/Viscid/archive/1.0.0.zip
Keywords: visualization,physics
Platform: UNKNOWN
Classifier: Programming Language :: Python :: 2.6
Classifier: Programming Language :: Python :: 2.7
Classifier: Programming Language :: Python :: 3
Classifier: Programming Language :: Python :: 3.3
Classifier: Programming Language :: Python :: 3.4
Classifier: Programming Language :: Python :: 3.5
Classifier: Programming Language :: Python :: 3.6
Classifier: Programming Language :: Python :: 3.7
Classifier: License :: OSI Approved :: MIT License
Classifier: Operating System :: OS Independent
Classifier: Topic :: Scientific/Engineering
Classifier: Topic :: Scientific/Engineering :: Physics
Classifier: Topic :: Scientific/Engineering :: Visualization
Requires-Dist: numpy (>=1.9)
